{
  "my_handle": "newenglandtopnews.bsky.social",
  "app_password_env_var": "BLUESKY_APP_PASSWORD_ne_news",
  "database": {
    "db_path": "/Users/hdon/Projects/Firebase/real-time/bsky-firehose/python/bsky/v2/bluesky_social.db",
    "followers_table": "ne_followers",
    "following_table": "ne_following"
  },
  "targets": {
    "target_a": "newenglandtopnews.bsky.social",
    "target_b": [
      "onestpress.onestnetwork.com"
    ]
  },
  "files": {
    "dry_run_log_file": "/Users/hdon/Projects/Firebase/real-time/bsky-firehose/python/bsky/dry_run_matches/ne_news_dry_run_matches.jsonl",
    "cursor_file": "/Users/hdon/Projects/Firebase/real-time/bsky-firehose/python/bsky/last_follow_cursors/ne_news_last_follower_cursor.txt",
    "auto_follow_log": "/Users/hdon/Projects/Firebase/real-time/bsky-firehose/python/bsky/auto_follow_logs/ne_news_auto_follow_log.jsonl"
  },
  "controls": {
    "keywords": [
      "Journalist",
      "News",
      "Epstein",
      "New York",
      "NY",
      "NYC",
      "Brooklyn",
      "BK",
      "BKLYN",
      "The Bronx",
      "BX",
      "Manhattan",
      "Queens",
      "Staten Island",
      "Coney Island",
      "Long Island",
      "LI",
      "Upstate NY",
      "Hudson Valley",
      "Westchester",
      "Albany",
      "Buffalo",
      "Rochester",
      "Syracuse",
      "Yonkers",
      "The Five Boroughs",
      "The City",
      "Gotham",
      "Tri-State",
      "Empire State",
      "MTA",
      "Subway",
      "LIRR",
      "Metro-North",
      "Park Slope",
      "Williamsburg",
      "Harlem",
      "LES",
      "UES",
      "UWS",
      "SoHo",
      "Astoria",
      "New Jersey",
      "NJ",
      "Jersey City",
      "Newark",
      "Trenton",
      "Paterson",
      "Princeton",
      "Hoboken",
      "Atlantic City",
      "Garden State",
      "Jersey Shore",
      "North Jersey",
      "South Jersey",
      "Central Jersey",
      "The Shore",
      "New Hampshire",
      "NH",
      "Manchester",
      "Nashua",
      "Concord",
      "Portsmouth",
      "Granite State",
      "White Mountains",
      "603",
      "Mt Washington",
      "Lake Winnipesaukee",
      "Winnipesaukee",
      "Seacoast NH",
      "Dartmouth",
      "Hanover NH",
      "Keene",
      "Dover NH",
      "Merrimack Valley",
      "North Country",
      "Lakes Region",
      "Nebraska",
      "NE",
      "Omaha",
      "Lincoln",
      "Cornhusker State",
      "Big Red",
      "Connecticut",
      "CT",
      "Hartford",
      "Stamford",
      "New Haven",
      "Bridgeport",
      "Waterbury",
      "Constitution State",
      "Delaware",
      "DE",
      "Wilmington",
      "Dover",
      "Newark DE",
      "First State",
      "Blue Hen",
      "District of Columbia",
      "DC",
      "Washington DC",
      "The District",
      "Capitol Hill",
      "The Hill",
      "Beltway",
      "Maryland",
      "MD",
      "Baltimore",
      "Bmore",
      "Annapolis",
      "Silver Spring",
      "Bethesda",
      "Rockville",
      "Old Line State",
      "Free State",
      "Charm City",
      "DMV",
      "Delmarva",
      "Pennsylvania",
      "PA",
      "Philadelphia",
      "Philly",
      "Pittsburgh",
      "Harrisburg",
      "Allentown",
      "Scranton",
      "Keystone State",
      "Quaker State",
      "Delco",
      "Chesco",
      "Montco",
      "Main Line",
      "Virginia",
      "VA",
      "Richmond",
      "RVA",
      "Virginia Beach",
      "Norfolk",
      "Alexandria",
      "Arlington",
      "NoVa",
      "Old Dominion",
      "Tidewater",
      "Vermont",
      "VT",
      "Burlington",
      "Montpelier",
      "Green Mountain State",
      "Green Mountains",
      "802",
      "BTV",
      "Lake Champlain",
      "Champlain Valley",
      "Stowe",
      "Rutland",
      "Brattleboro",
      "Middlebury",
      "Bennington",
      "Northeast Kingdom",
      "NEK",
      "Rhode Island",
      "RI",
      "Providence",
      "Newport",
      "Ocean State",
      "Little Rhody",
      "Maine",
      "ME",
      "Portland ME",
      "Augusta",
      "Bangor",
      "Pine Tree State",
      "Vacationland",
      "Downeast",
      "Down East",
      "207",
      "Acadia",
      "Bar Harbor",
      "Lewiston",
      "Auburn ME",
      "Midcoast",
      "Midcoast Maine",
      "Casco Bay",
      "Kennebunkport",
      "Orono",
      "New England",
      "N.E.",
      "East Coast",
      "EST",
      "ET",
      "Acela Corridor",
      "Massachusetts",
      "Cambridge",
      "MA",
      "Boston",
      "Reporter",
      "Journalist",
      "Anchor",
      "News",
      "Correspondent",
      "Editor",
      "Press",
      "Media",
      "Newsroom",
      "Writer",
      "Freelance"
    ],
    "max_per_run": 5000
  },
  "api": {
    "base_url": "https://bsky.social/xrpc"
  },
  "tool": {
    "pagination_delay": 0.6,
    "max_profiles_per_batch": 25,
    "heartbeat_interval_minutes": 2
  }
}
